{
  "poll_responses": {
    "call": [
      "Convoco al concejo para infundir luz en el camino incierto",
      "El tiempo de la deliberación ha llegado",
      "Que los ecos de nuestros ancestros guíen nuestras decisiones",
      "Llamo a las sombras para que presencien este momento",
      "Invoco la sabiduría de aquellos iluminados que componen el consejo"
    ],
    "mute_yes": [
      "Se ha erradicado la fruta podrida, para evitar que infecte la fruta sana",
      "La mala hierba fue cortada.",
      "A aquel que osa perturbar las aguas calmadas de nuestro pueblo, MUERTE!",
      "Los que han caído en la oscuridad no conocerán la luz otra vez",
      "Los enemigos del culto han sido silenciados, el camino está despejado"
    ],
    "mute_no": [
      "Bienaventurado aquel que encuentra el perdón ante el juicio del consejo",
      "La redención ha sido otorgada por los sabios del consejo",
      "Aún hay esperanza en la penumbra, el perdón es un camino",
      "Que la misericordia prevalezca sobre el juicio",
      "Las puertas de la absolución permanecen abiertas para quienes lo deseen"
    ],
    "mute_neutral": [
      "No se alcanzó la cantidad de votos del concejo, la decisión queda en suspenso",
      "Las voces de los ancianos no fueron escuchadas, debemos volver a convocar",
      "El eco de la decisión aún resuena en la oscuridad, aguardemos más tiempo",
      "No hay consenso entre los fieles, el camino permanece incierto",
      "La votación ha sido insuficiente; quizás los dioses aún no están listos"
    ]
  },
  "actions": {
    "kick": [
      "Has sido desterrado por decreto del Consejo. Sólo los fieles de corazón puro pueden caminar entre las sombras de este santuario.",
      "El Consejo ha hablado y tus pasos se desvanecen del templo. Solo aquellos que guardan reverencia encuentran lugar en nuestro círculo.",
      "Las sendas de los fieles no son para los errantes. Tu exilio es la voluntad del Consejo.",
      "El Consejo te aleja de su presencia, pues los votos ya no están contigo.",
      "El sendero del Consejo se estrecha para los indignos. Hoy te apartas de la senda."
    ],
    "mute": [
      "El Consejo dicta silencio. Enmudece, y que la quietud te revele la senda de redención.",
      "Los murmullos del Consejo te sellan los labios. Que el silencio te guíe a la verdad.",
      "Que el Consejo te imponga el manto del silencio, solo en la quietud hallarás paz.",
      "El eco de tus palabras se desvanece; el Consejo decreta silencio.",
      "Por mandato del Consejo, tu voz se apaga en este sagrado recinto."
    ],
    "ban": [
      "Por orden del Consejo, eres exiliado a las sombras perpetuas. Tu ausencia honrará a los devotos verdaderos.",
      "El Consejo te destierra de nuestra sagrada morada. La eternidad se torna oscura para los que renuncian al culto.",
      "Los que desafían el Consejo son arrojados al vacío eterno. Tu regreso jamás será contemplado.",
      "El abismo te acoge, desterrado por el Consejo. Aquí no hallarás cabida.",
      "El Consejo ha sellado tu destino: solo la penumbra eterna será testigo de tu caída."
    ],
    "member_join": [
      "Bienvenido, peregrino del Consejo. ¿Traes el espíritu digno para morar en este santuario?",
      "La puerta del Consejo se abre para ti, recién llegado. Que la penumbra te envuelva y te ilumine a la vez.",
      "Que los susurros del Consejo te guíen, alma inquieta, en este sendero de sombras.",
      "El Consejo ha recibido tu presencia. ¿Serás uno con la penumbra?",
      "Las puertas oscuras del Consejo se abren a una nueva alma. Bienvenido al círculo."
    ],
    "member_leave": [
      "Tu sombra abandona el Consejo, pero la oscuridad recuerda a los que se marchan.",
      "El Consejo te observa partir, y los ecos de tu ausencia resuenan en sus muros.",
      "A tu partida, el Consejo se lamenta, pero aquellos que abandonan no siempre encuentran retorno.",
      "La penumbra del Consejo se densifica en tu ausencia. Partes, pero no sin dejar una sombra.",
      "Los fieles observan en silencio tu retirada. Que encuentres lo que buscas fuera del Consejo."
    ],
    "role_add": [
      "El Consejo te ha concedido un nuevo título, un ascenso en tu senda de devoción.",
      "Te has ganado el favor del Consejo; con este rol vienes a ocupar un lugar entre los más fieles.",
      "Tu espíritu ha ascendido en la jerarquía sagrada. Honra al Consejo en cada acto.",
      "El Consejo te eleva; lleva este rol como una llama en la oscuridad.",
      "Los votos se han pronunciado, y con ello te has ganado el ascenso. El Consejo confía en ti."
    ],
    "role_remove": [
      "El Consejo retira su favor; un rol se desvanece, como las sombras al amanecer.",
      "Despojado por mandato del Consejo, vuelve a la senda y recobra tu favor en silencio.",
      "El Consejo te degrada, tu posición entre los fieles ha sido revisada. Persevera.",
      "El rol que portabas ya no te corresponde; enmienda tu senda o busca redención.",
      "El Consejo ha hablado, y tu jerarquía ha cambiado. Que esta pérdida te inspire humildad."
    ],
    "duel_accept": [
      "El Consejo observa con expectación tu aceptación. Que este duelo decida el digno.",
      "Se llama al combate; el Consejo ha sancionado este duelo. Prepárate.",
      "El desafío ha sido aceptado bajo la mirada del Consejo. Que el duelo comience.",
      "Tu aceptación resuena en los salones del Consejo. Solo uno prevalecerá.",
      "Que los osados sean bienvenidos al duelo, por decreto del Consejo."
    ],
    "duel_reject": [
      "El Consejo ha recibido tu rechazo. La contienda no tendrá lugar.",
      "El duelo es rechazado. A veces, el honor del Consejo yace en la prudencia.",
      "El Consejo ha decidido en contra del duelo; el desafío se desvanece en las sombras.",
      "Con sabiduría, el duelo es rechazado. El Consejo acepta tu decisión.",
      "Tu negativa es escuchada por el Consejo, y así se evita el derramamiento."
    ],
    "duel_timeout": [
      "El Consejo suspira, pues el duelo ha caído en el olvido. El desafío no ha sido respondido.",
      "El tiempo ha expirado, y el duelo se disuelve en la penumbra. El Consejo permanece en silencio.",
      "El Consejo aguarda en vano, pero el duelo no ha sido atendido.",
      "Que la falta de respuesta sea vista como señal. El Consejo desiste del desafío.",
      "El eco del duelo se desvanece en la oscuridad; el Consejo retira su convocatoria."
    ]
  },
  "images": {
    "council": [
      "council_00.png",
      "council_01.png",
      "council_02.png"
    ],
    "member": [
      "m_patricio.png",
      "m_bobesponja.png",
      "m_calamardo.png"
    ]
  }
}
